Workbook

Sheet Dashboard
A1: 财务与人力资源推演模型 - Dashboard
A3: 参数输入区
A5: 1.1 薪酬参数 (Compensation Parameters)
A6: 参数名称 | B6: 默认值 | C6: 单位 | D6: 描述与来源
A7: 制作节点
A8: 内审通过基础薪酬 | B8: 5 | C8: 元/工作单位 | D8: 基于完成并通过内审的报酬 (引用元规则 XC-1-1 参数1)
A9: 外审通过额外薪酬 | B9: 10 | C9: 元/工作单位 | D9: 交付成果最终通过外审的额外奖励 (引用元规则 XC-1-1 参数2)
A10: S级月度奖金 | B10: 500 | C10: 元/月 | D10: 当月保持S级状态获得的固定奖金 (引用元规则 XC-1-2 参数1)
A11: 培训节点
A12: 团队服务内审薪酬 | B12: 0 | C12: 元/工作单位 | D12: 基于团队完成的工作单位，给培训节点的内审部分提成 (引用元规则 XC-1-1 参数1)
A13: 团队服务外审薪酬 | B13: 1 | C13: 元/工作单位 | D13: 基于团队完成的工作单位，给培训节点的外审部分提成 (引用元规则 XC-1-1 参数2)
A14: S级团队保持奖金 | B14: 100 | C14: 元/人 | D14: 根据月末团队中S级成员数量发放的奖金 (引用元规则 XC-1-2 参数1)
A15: 完成基础培训薪酬 | B15: 100 | C15: 元/人 | D15: 成功完成一名组员的基础培训所得奖励 (引用元规则 XC-2-1 参数1)
A16: 新晋升S级培训薪酬 | B16: 200 | C16: 元/人 | D16: 成功将一名组员培养至S级所得奖励 (引用元规则 XC-2-1 参数2)
A17: 节点晋升激励奖金 | B17: 1000 | C17: 元/人 | D17: 培养的组员晋升为新培训节点时的一次性奖励 (引用元规则 XC-2-2 参数1)
A18: 内审节点
A19: 有效审核薪酬 | B19: -4 | C19: 元/次 | D19: 内审通过后，一次性通过外审的审核报酬 (引用元规则 XC-3-1 参数1)
A20: 无效审核薪酬 | B20: 0 | C20: 元/次 | D20: 内审通过后，未能一次性通过外审的审核报酬 (引用元规则 XC-3-1 参数2)
A21: 项目管理节点
A22: 订单全流程跟踪费 | B22: 1 | C22: 元/单 | D22: 完整跟进一个订单全流程的报酬 (引用元规则 XC-4-1 参数1)
A25: 1.2 业务核心参数 (Core Business Parameters)
A26: 参数名称 | B26: 默认值 | C26: 单位 | D26: 描述
A27: 订单定价 | B27: 30 | C27: 元/工作单位 | D27: 我们对客户就每个工作单位的报价
A28: 平均弃单率 | B28: 0.2 | C28: % | D28: 制作节点在任务周期内放弃订单的平均比率
A29: 平均外审一次通过率 | B29: 0.4 | C29: % | D29: 内审通过的订单，首次提交给甲方审核的通过率
A30: 平均外审通过率 | B30: 0.95 | C30: % | D30: 订单最终通过外审的比率
A31: 平均内审次数 | B31: 1.5 | C31: 次/工作单位 | D31: 单个工作单位从首次提交到通过内审，平均需要经历的内审次数
A34: 1.3 人力与效率参数 (HR & Efficiency Parameters)
A36: 1.3.1 产能与规模 (Capacity & Scale)
A37: 参数名称 | B37: 默认值 | C37: 单位 | D37: 描述
A38: 制作节点
A39: 月度工作单位容量 | B39: 150 | C39: 工作单位/月 | D39: 一位标准的S级制作节点一个月的平均产能
A40: 培训节点
A41: 团队规模 | B41: 20 | C41: 人/团队 | D41: 一位培训节点平均带领的制作节点数量
A42: 内审节点
A43: 月度审核总次数 | B43: 2000 | C43: 次/月 | D43: 一位标准的内审节点一个月的平均审核次数
A44: 项目管理节点
A45: 月度跟踪订单总数 | B45: 1000 | C45: 单/月 | D45: 一位标准的项目管理节点一个月的平均跟踪订单数
A46: 运营模拟
A47: 总S级制作节点数 | B47: 30 | C47: 人 | D47: 用于模拟计算整体项目毛利率的团队规模基数
A51: 1.3.2 人力转化漏斗 (HR Conversion Funnel)
A52: 参数名称 | B52: 默认值 | C52: 单位 | D52: 描述
A53: 每月新招募总人数 | B53: 20 | C53: 人/月 | D53: 每月新进入培训流程的总人数
A54: 基础培训转化率 | B54: 0.8 | C54: % | D54: 新招募成员中，能完成基础培训的比例
A55: S级晋升转化率 | B55: 0.3 | C55: % | D55: 完成基础培训的成员中，最终能晋升为S级的比例
A56: S级成员晋升培训节点转化率 | B56: 0.05 | C56: %/月 | D56: 团队中S级成员，平均每月晋升为新培训节点的比率
A57: 制作节点平均生命周期 | B57: 6 | C57: 月 | D57: 一个制作节点从入职到离職的平均时长
A58: 月均培训学员数(单培训节点) | B58: 10 | C58: 人/月 | D58: 单个培训节点平均每月承接的新培训学员数量
A62: 1.3.3 时间成本 (Time Cost)
A63: 参数名称 | B63: 默认值 | C63: 单位 | D63: 描述
A64: 原子动作耗时
A65: 单工作单位平均制作耗时 | B65: 0.5 | C65: 小时/工作单位
A66: 单次内审平均耗时 | B66: 0.08 | C66: 小时/次
A67: 单次订单跟踪平均耗时 | B67: 0.32 | C67: 小时/单
A68: 单个学员培训管理月均耗时 | B68: 4 | C68: 小时/人/月 | D68: 培训节点投入在单个学员上的月均时间
A73: 核心指标展示区 (Key Metrics Display)
A75: 盈利能力 (Profitability)
A76: 指标名称 | B76: 数值 | C76: 单位
A77: 单工作单位毛利 | B77: =模型计算!C117 -> 15.3 | C77: 元/工作单位
A78: 单S级节点月度毛利 | B78: =模型计算!C118 -> 1695 | C78: 元/月
A79: 整体项目毛利率 | B79: =IFERROR(模型计算!C124,0) -> 0.36125926 | C79: %
A81: 节点价值 (Node Value)
A82: 单节点LTV | B82: =模型计算!C126 -> 9736.6667 | C82: 元
A84: 薪酬效率 (Compensation Efficiency)
A85: 制作节点
A86: 月薪 | B86: =模型计算!C129 -> 2675 | C86: 元/月
A87: 月均工时 | B87: =模型计算!C130 -> 75 | C87: 小时/月
A88: 时薪 | B88: =模型计算!C131 -> 35.666667 | C88: 元/小时
A90: 培训节点
A91: 月薪 | B91: =模型计算!C134 -> 7130 | C91: 元/月
A92: 月均工时 | B92: =模型计算!C135 -> 100 | C92: 小时/月
A93: 时薪 | B93: =IFERROR(模型计算!C136,"-") -> 71.3 | C93: 元/小时
A95: 内审节点
A96: 月薪 | B96: =模型计算!C139 -> -3200 | C96: 元/月
A97: 月均工时 | B97: =模型计算!C140 -> 160 | C97: 小时/月
A98: 时薪 | B98: =模型计算!C141 -> -20 | C98: 元/小时
A100: 项目管理节点
A101: 月薪 | B101: =模型计算!C144 -> 1000 | C101: 元/月
A102: 月均工时 | B102: =模型计算!C145 -> 0 | C102: 小时/月
A103: 时薪 | B103: =IFERROR(模型计算!C146,"-") -> 0 | C103: 元/小时
A108: 注："-"表示该值无法计算（可能由于除零或参数缺失）

Sheet 模型计算
A1: 模型计算引擎 (Calculation Engine)
A3: 区域A：参数链接区
A5: 1.1 薪酬参数
A6: 参数名称 | B6: 数值 | C6: 单位
A7: 制作节点
A8: 内审通过基础薪酬 | B8: =Dashboard!B8 -> 5 | C8: 元/工作单位
A9: 外审通过额外薪酬 | B9: =Dashboard!B9 -> 10 | C9: 元/工作单位
A10: S级月度奖金 | B10: =Dashboard!B10 -> 500 | C10: 元/月
A11: 培训节点
A12: 团队服务内审薪酬 | B12: =Dashboard!B12 -> 0 | C12: 元/工作单位
A13: 团队服务外审薪酬 | B13: =Dashboard!B13 -> 1 | C13: 元/工作单位
A14: S级团队保持奖金 | B14: =Dashboard!B14 -> 100 | C14: 元/人
A15: 完成基础培训薪酬 | B15: =Dashboard!B15 -> 100 | C15: 元/人
A16: 新晋升S级培训薪酬 | B16: =Dashboard!B16 -> 200 | C16: 元/人
A17: 节点晋升激励奖金 | B17: =Dashboard!B17 -> 1000 | C17: 元/人
A18: 内审节点
A19: 有效审核薪酬 | B19: =Dashboard!B19 -> -4 | C19: 元/次
A20: 无效审核薪酬 | B20: =Dashboard!B20 -> 0 | C20: 元/次
A21: 项目管理节点
A22: 订单全流程跟踪费 | B22: =Dashboard!B22 -> 1 | C22: 元/单
A25: 1.2 业务核心参数
A26: 参数名称 | B26: 数值 | C26: 单位
A27: 订单定价 | B27: =Dashboard!B27 -> 30 | C27: 元/工作单位
A28: 平均弃单率 | B28: =Dashboard!B28 -> 0.2 | C28: %
A29: 平均外审一次通过率 | B29: =Dashboard!B29 -> 0.4 | C29: %
A30: 平均外审通过率 | B30: =Dashboard!B30 -> 0.95 | C30: %
A31: 平均内审次数 | B31: =Dashboard!B31 -> 1.5 | C31: 次/工作单位
A34: 1.3 人力与效率参数
A36: 1.3.1 产能与规模
A37: 参数名称 | B37: 数值 | C37: 单位
A38: 制作节点
A39: 月度工作单位容量 | B39: =Dashboard!B39 -> 150 | C39: 工作单位/月
A40: 培训节点
A41: 团队规模 | B41: =Dashboard!B41 -> 20 | C41: 人/团队
A42: 内审节点
A43: 月度审核总次数 | B43: =Dashboard!B43 -> 2000 | C43: 次/月
A44: 项目管理节点
A45: 月度跟踪订单总数 | B45: =Dashboard!B45 -> 1000 | C45: 单/月
A46: 运营模拟
A47: 总S级制作节点数 | B47: =Dashboard!B47 -> 30 | C47: 人
A50: 1.3.2 人力转化漏斗
A51: 参数名称 | B51: 数值 | C51: 单位
A52: 每月新招募总人数 | B52: =Dashboard!B53 -> 20 | C52: 人/月
A53: 基础培训转化率 | B53: =Dashboard!B54 -> 0.8 | C53: %
A54: S级晋升转化率 | B54: =Dashboard!B55 -> 0.3 | C54: %
A55: S级成员晋升培训节点转化率 | B55: =Dashboard!B56 -> 0.05 | C55: %/月
A56: 制作节点平均生命周期 | B56: =Dashboard!B57 -> 6 | C56: 月
A57: 月均培训学员数(单培训节点) | B57: =Dashboard!B58 -> 10 | C57: 人/月
A60: 1.3.3 时间成本
A61: 参数名称 | B61: 数值 | C61: 单位
A62: 原子动作耗时
A63: 单工作单位平均制作耗时 | B63: =Dashboard!B65 -> 0.5 | C63: 小时/工作单位
A64: 单次内审平均耗时 | B64: =Dashboard!B66 -> 0.08 | C64: 小时/次
A65: 单次订单跟踪平均耗时 | B65: =Dashboard!B67 -> 0.32 | C65: 小时/单
A66: 单个学员培训管理月均耗时 | B66: =Dashboard!B68 -> 4 | C66: 小时/人/月
A71: 区域B：单工作单位订单模型计算
A73: 成本构成项 | B73: 计算公式 | C73: 结果（元/工作单位） | D73: 备注
A74: 单位内审相关成本 | D74: 这部分成本受"弃单率"影响，因为弃单后需要重新分配，再次产生内审成本
A75: 制作节点内审薪酬 | B75: 内审通过基础薪酬 | C75: =B8 -> 5
A76: 培训节点团队服务内审薪酬 | B76: 团队服务内审薪酬 | C76: =B12 -> 0
A77: 小计：单位内审名义成本 | B77: (制作)内审薪酬 + (培训)内审薪酬 | C77: =C75+C76 -> 5
A78: 内审节点审核成本 | B78: ((有效审核薪酬 * 外审一次通过率) + (无效审核薪酬 * (1 - 外审一次通过率))) * 平均内审次数 | C78: =((B19*B29)+(B20*(1-B29)))*B31 -> -2.4 | D78: ((0 * 0.7) + (3 * 0.3)) * 1.5
A79: 单位内审实际成本 (含弃单) | B79: (单位内审名义成本 + 内审节点审核成本) / (1 - 平均弃单率) | C79: =(C77+C78)/(1-B28) -> 3.25 | D79: (10 + 1.35) / (1 - 0.2)
A80: 单位外审相关成本 | D80: 这部分成本只有在最终交付成功时产生
A81: 制作节点外审薪酬 | B81: 外审通过额外薪酬 | C81: =B9 -> 10
A82: 培训节点团队服务外审薪酬 | B82: 团队服务外审薪酬 | C82: =B13 -> 1
A83: 小计：单位外审成本 | B83: (制作)外审薪酬 + (培训)外审薪酬 | C83: =C81+C82 -> 11
A84: 项目管理成本
A85: 订单跟踪成本 | B85: 订单全流程跟踪费 | C85: =B22 -> 1 | D85: 假设一个工作单位对应一个订单的跟踪
A86: 总计：每工作单位交付成本 | B86: 单位内审实际成本 + 单位外审成本 * 平均外审通过率 + 订单跟踪成本 | C86: =C79+C83*B30+C85 -> 14.7 | D86: 14.1875 + 10 * 0.95 + [待定]
A90: 区域C：AAARRR模型计算
A92: 3.1 成本分析 (Cost Analysis)
A93: 环节 | B93: 子项 | C93: 计算公式 | D93: 结果（元/人） | E93: 备注
A94: Acquisition (招募)
A95: G-HR 渠道与人力成本 | B95: [待定] | C95: [待定] | D95: 100 | E95: 暂未参数化，可设为固定值
A96: Activation (激活/培训) | D96: =B16+((1/B54)-1)*B15 -> 433.33333
A97: 单S级节点总培训成本 | B97: (新晋升S级培训薪酬) + ((1 / S级晋升转化率) - 1) * 完成基础培训薪酬 | D97: =B16+((1/B54)-1)*B15 -> 433.33333 | E97: 100 + ((1 / 0.3) - 1) * 200
A98: Retention (留存) | D98: =B10 -> 500
A99: 制作节点S级月度奖金 | B99: S级月度奖金 | D99: =B14 -> 100
A100: 培训节点S级团队保持奖金 | B100: S级团队保持奖金 | C100: =B14 -> 100 | D100: =D98+D99 -> 600
A101: 小计：单S级节点月度留存成本 | B101: (制作)S级奖金 + (培训)S级奖金 | C101: =D98+D99 -> 600 | D101: =D98+D99 -> 600
A103: 3.2 收益分析 (Revenue Analysis)
A104: 收益项 | B104: 计算公式 | C104: 结果 | D104: 备注
A105: 单S级节点月度贡献
A106: 月度贡献工作单位 | B106: 月度工作单位容量 | C106: =B39 -> 150 | D106: 工作单位
A107: 月度贡献订单收入 | B107: 月度工作单位容量 * 订单定价 | C107: =B39*B27 -> 4500
A108: 月度贡献订单毛利 | B108: 月度贡献订单收入 - (月度工作单位容量 * 每工作单位交付成本) | C108: =C107-(B39*C86) -> 2295
A113: 区域D：核心指标计算
A115: 指标名称 | B115: 计算公式 | C115: 结果 | D115: 备注
A116: 盈利能力 (Profitability)
A117: 单工作单位毛利 | B117: 订单定价 - 每工作单位交付成本 | C117: =B27-C86 -> 15.3 | D117: 元/工作单位
A118: 单S级节点月度毛利 | B118: 月度贡献订单毛利 - 单S级节点月度留存成本 | C118: =C108-D100 -> 1695 | D118: 元/月
A119: 整体运营模拟 (Overall Simulation) | D119: 为计算整体毛利率，需先定义以下过程变量
A120: 每月新S级节点数 | B120: 每月新招募总人数 * 基础培训转化率 * S级晋升转化率 | C120: =B52*B53*B54 -> 4.8 | D120: 人
A121: 总收入 | B121: 总S级制作节点数 * 月度工作单位容量 * 订单定价 | C121: =B47*B39*B27 -> 135000 | D121: 元
A122: 总订单成本 | B122: 总S级制作节点数 * 月度工作单位容量 * 每工作单位交付成本 | C122: =B47*B39*C86 -> 66150 | D122: 元
A123: 总AAARRR成本 | B123: (每月新S级节点数 * 单S级节点总培训成本) + (总S级制作节点数 * 单S级节点月度留存成本) | C123: =(C120*D96)+(B47*D100) -> 20080 | D123: 元
A124: 整体项目毛利率 | B124: (总收入 - 总订单成本 - 总AAARRR成本) / 总收入 | C124: =IF(C121=0,0,(C121-C122-C123)/C121) -> 0.36125926 | D124: 综合指标，需基于团队总规模进行测算
A125: 节点价值 (Node Value)
B126: 单S级节点月度毛利 * 制作节点平均生命周期 - 单S级节点总培训成本 | C126: =C118*B56-D96 -> 9736.6667 | D126: 衡量一个制作节点在其生命周期内能带来的总价值
...

Sheet 数据源
A1: 数据源 (Data Sources)
A3: 角色列表
A4: 制作节点
A5: 培训节点
A6: 内审节点
A7: 项目管理节点
A9: 参数单位列表
A10: 元/工作单位
A11: 元/月
A12: 元/人
A13: 元/次
A14: 元/单
... A27: 小时/人/月
